redisex/__init__.py
redisex/redisex.py
redisex-0.0.9.dist-info/LICENSE.txt
redisex-0.0.9.dist-info/METADATA
redisex-0.0.9.dist-info/WHEEL
redisex-0.0.9.dist-info/top_level.txt
redisex-0.0.9.dist-info/RECORD
